ghanon/__init__.py
ghanon/cli.py
ghanon/formatter.py
ghanon/logger.py
ghanon/parser.py
ghanon/yaml.py
ghanon/domain/__init__.py
ghanon/domain/base.py
ghanon/domain/concurrency.py
ghanon/domain/container.py
ghanon/domain/defaults.py
ghanon/domain/enums.py
ghanon/domain/environment.py
ghanon/domain/events.py
ghanon/domain/jobs.py
ghanon/domain/matrix.py
ghanon/domain/permissions.py
ghanon/domain/runner.py
ghanon/domain/step.py
ghanon/domain/triggers.py
ghanon/domain/types.py
ghanon/domain/workflow.py
ghanon-0.2.1.dist-info/METADATA
ghanon-0.2.1.dist-info/WHEEL
ghanon-0.2.1.dist-info/entry_points.txt
ghanon-0.2.1.dist-info/licenses/LICENSE
ghanon-0.2.1.dist-info/RECORD
