Metadata-Version: 2.4
Name: ghanon
Version: 0.2.1
Summary: The GitHub Actions Best Practices Linter
Project-URL: homepage, https://github.com/nikoheikkila/ghanon
Project-URL: repository, https://github.com/nikoheikkila/ghanon.git
Project-URL: documentation, https://github.com/nikoheikkila/ghanon/blob/master/README.md
Project-URL: changelog, https://github.com/nikoheikkila/ghanon/blob/master/CHANGELOG.md
Project-URL: issues, https://github.com/nikoheikkila/ghanon/issues
Author-email: Niko Heikkilä <yo@nikoheikkila.fi>
License: MIT License
License-File: LICENSE
Keywords: actions,best practices,ci/cd,github,linter
Classifier: Framework :: Pydantic
Classifier: Framework :: Pydantic :: 2
Classifier: Intended Audience :: Developers
Classifier: License :: OSI Approved :: MIT License
Classifier: Operating System :: OS Independent
Classifier: Programming Language :: Python :: 3.14
Classifier: Topic :: Software Development :: Libraries :: Python Modules
Classifier: Topic :: Software Development :: Quality Assurance
Classifier: Topic :: Software Development :: Testing
Classifier: Typing :: Typed
Requires-Python: >=3.14
Requires-Dist: click>=8.3.1
Requires-Dist: colorama>=0.4.6
Requires-Dist: pydantic>=2.12.5
Requires-Dist: pyyaml>=6.0.2
